AUTHORS
LICENSE
MANIFEST.in
README.rst
setup.py
django_scheduled_blocks.egg-info/PKG-INFO
django_scheduled_blocks.egg-info/SOURCES.txt
django_scheduled_blocks.egg-info/dependency_links.txt
django_scheduled_blocks.egg-info/not-zip-safe
django_scheduled_blocks.egg-info/top_level.txt
scheduled_blocks/__init__.py
scheduled_blocks/admin.py
scheduled_blocks/models.py
scheduled_blocks/tests.py
scheduled_blocks/views.py
scheduled_blocks/migrations/0001_initial.py
scheduled_blocks/migrations/__init__.py
scheduled_blocks/templatetags/__init__.py
scheduled_blocks/templatetags/scheduled_blocks_tags.py