Metadata-Version: 1.1
Name: django-scheduled-blocks
Version: 0.0.1
Summary: A quick and dirty app to schedule content in django templates
Home-page: https://github.com/pgcd/scheduled_blocks
Author: Paolo Dente
Author-email: pgcd93@gmail.com
License: Simplified BSD
Platform: UNKNOWN
Classifier: Topic :: Internet :: WWW/HTTP :: Dynamic Content
Classifier: Intended Audience :: Developers
Classifier: Programming Language :: Python
Classifier: Programming Language :: Python :: 2.6
Classifier: Programming Language :: Python :: 2.7
Classifier: Framework :: Django
Classifier: Development Status :: 4 - Beta
Classifier: Operating System :: OS Independent
